brama/__init__.py
brama/api.py
brama/app.py
brama/cli.py
brama/default_config.py
brama/handlers.py
brama/plugins.py
brama/registry.py
brama/request.py
brama/route.py
brama/utils.py
brama/contrib/__init__.py
brama/contrib/plugins/__init__.py
brama/contrib/plugins/authorization.py
brama/contrib/plugins/jwt_auth.py
brama/contrib/plugins/rate_limiting.py
brama-0.0.1rc1.dist-info/DESCRIPTION.rst
brama-0.0.1rc1.dist-info/LICENSE.txt
brama-0.0.1rc1.dist-info/METADATA
brama-0.0.1rc1.dist-info/RECORD
brama-0.0.1rc1.dist-info/WHEEL
brama-0.0.1rc1.dist-info/entry_points.txt
brama-0.0.1rc1.dist-info/metadata.json
brama-0.0.1rc1.dist-info/top_level.txt
